deplacecli/__init__.py
deplacecli/cli.py
deplacecli/commands.py
deplacecli/draw.py
deplacecli/storage.py
deplacecli/utils.py
deplace_cli-0.1.54.dist-info/METADATA
deplace_cli-0.1.54.dist-info/WHEEL
deplace_cli-0.1.54.dist-info/entry_points.txt
deplace_cli-0.1.54.dist-info/top_level.txt
deplace_cli-0.1.54.dist-info/RECORD
