Metadata-Version: 2.4
Name: deplace-cli
Version: 0.1.54
Summary: A CLI tool to access Deplace Datasets.
Home-page: https://www.depalceai.com
Author: Deplace AI
Author-email: admin@deplaceai.com
License: MIT
Classifier: Programming Language :: Python :: 3
Classifier: License :: OSI Approved :: MIT License
Classifier: Operating System :: OS Independent
Requires-Python: >=3.7
Requires-Dist: azure-storage-blob
Requires-Dist: opencv-python
Requires-Dist: numpy
Requires-Dist: pycocotools
Requires-Dist: tqdm
Dynamic: author
Dynamic: requires-dist
Dynamic: summary
